pydjinni/__init__.py
pydjinni/__main__.py
pydjinni/api.py
pydjinni/defs.py
pydjinni/exceptions.py
pydjinni/lexer.py
pydjinni/position.py
pydjinni/builder/__init__.py
pydjinni/builder/build_config.py
pydjinni/builder/target.py
pydjinni/builder/conan/__init__.py
pydjinni/builder/conan/config_model.py
pydjinni/builder/conan/target.py
pydjinni/cli/cli.py
pydjinni/cli/context.py
pydjinni/cmake/modules/FindPyDjinni.cmake
pydjinni/cmake/modules/PyDjinni.cmake
pydjinni/config/config_model_builder.py
pydjinni/config/types.py
pydjinni/file/file_reader_writer.py
pydjinni/file/processed_files_model_builder.py
pydjinni/generator/__init__.py
pydjinni/generator/external_types.py
pydjinni/generator/filters.py
pydjinni/generator/generate_config.py
pydjinni/generator/generator.py
pydjinni/generator/metadata.py
pydjinni/generator/target.py
pydjinni/generator/validator.py
pydjinni/generator/cpp/__init__.py
pydjinni/generator/cpp/target.py
pydjinni/generator/cpp/cpp/comment_renderer.py
pydjinni/generator/cpp/cpp/config.py
pydjinni/generator/cpp/cpp/external_types.py
pydjinni/generator/cpp/cpp/filters.py
pydjinni/generator/cpp/cpp/generator.py
pydjinni/generator/cpp/cpp/keywords.py
pydjinni/generator/cpp/cpp/type.py
pydjinni/generator/cpp/cpp/support_lib/include/pydjinni/deprecated.hpp
pydjinni/generator/cpp/cpp/support_lib/include/pydjinni/exception.hpp
pydjinni/generator/cpp/cpp/support_lib/include/pydjinni/format.hpp
pydjinni/generator/cpp/cpp/support_lib/include/pydjinni/coroutine/continuation_awaitable.hpp
pydjinni/generator/cpp/cpp/support_lib/include/pydjinni/coroutine/continuation_runner.hpp
pydjinni/generator/cpp/cpp/support_lib/include/pydjinni/coroutine/task.hpp
pydjinni/generator/cpp/cpp/support_lib/include/pydjinni/type/binary.hpp
pydjinni/generator/cpp/cpp/templates/base.jinja2
pydjinni/generator/cpp/cpp/templates/header/enum.jinja2.hpp
pydjinni/generator/cpp/cpp/templates/header/error_domain.jinja2.hpp
pydjinni/generator/cpp/cpp/templates/header/flags.jinja2.hpp
pydjinni-1.0a9.dist-info/LICENSE
pydjinni-1.0a9.dist-info/METADATA
pydjinni-1.0a9.dist-info/WHEEL
pydjinni-1.0a9.dist-info/entry_points.txt
pydjinni-1.0a9.dist-info/top_level.txt
pydjinni-1.0a9.dist-info/RECORD
