Metadata-Version: 2.2
Name: pydjinni
Version: 1.0a9
Summary: An opinionated Djinni reimplementation written in Python.
Author-email: jothepro <pydjinni@jothe.pro>
Project-URL: Repository, https://github.com/pydjinni/pydjinni
Project-URL: Homepage, https://pydjinni.github.io/pydjinni
Keywords: djinni
Classifier: Intended Audience :: Developers
Classifier: License :: OSI Approved :: Apache Software License
Classifier: Programming Language :: Python :: 3
Classifier: Programming Language :: Python :: 3.13
Requires-Python: >=3.13
License-File: LICENSE
Requires-Dist: importlib-metadata<9,>=8.5
Requires-Dist: click<9,>=8.1
Requires-Dist: Jinja2<4,>=3.1
Requires-Dist: pydantic<3,>=2.11.0
Requires-Dist: pydantic-settings<3,>=2.9.0
Requires-Dist: rich<14,>=13.9
Requires-Dist: PyYAML<7,>=6
Requires-Dist: dotmap<2,>=1.3
Requires-Dist: tomli_w<2,>=1.0
Requires-Dist: setuptools>=75
Requires-Dist: antlr4-python3-runtime==4.13.2
Requires-Dist: mistune<4,>=3
Requires-Dist: pygls<2,>=1.3
Provides-Extra: dev
Requires-Dist: pytest==8.3.3; extra == "dev"
Requires-Dist: pytest-asyncio==0.25.3; extra == "dev"
Requires-Dist: pytest-lsp==0.4.3; extra == "dev"
Requires-Dist: coverage==7.6.12; extra == "dev"
Requires-Dist: antlr4-tools==0.2.1; extra == "dev"
Provides-Extra: publish
Requires-Dist: twine==6.1.0; extra == "publish"
Requires-Dist: build==1.0.3; extra == "publish"
Provides-Extra: doc
Requires-Dist: mkdocs-material==9.6.7; extra == "doc"
Requires-Dist: mkdocs-click==0.8.1; extra == "doc"
Requires-Dist: mike==2.1.3; extra == "doc"
Requires-Dist: jsonref==1.1.0; extra == "doc"
Requires-Dist: mkdocs-macros-plugin==1.3.7; extra == "doc"
Requires-Dist: mkdocs-gen-files==0.5.0; extra == "doc"
Requires-Dist: mkdocstrings[python]==0.27.0; extra == "doc"
Requires-Dist: setuptools_scm==8.1.0; extra == "doc"
